Workbook

Sheet Responses
A1: submitted_at | B1: contact_name | C1: contact_phone | D1: contact_email | E1: branch | F1: service_requested | G1: language | H1: source | I1: ces_find_channel | J1: ces_easy_handle | K1: resolution | L1: nps_score | M1: nps_reason | N1: csat_overall | O1: csat_as_advertised | P1: csat_expectations | Q1: csat_rep_knowledge | R1: csat_communication | S1: csat_response_time | T1: ces_avg | U1: csat_avg | V1: nps_category | W1: is_flagged | X1: followed_up_at | Y1: follow_up_notes
A2: 46204.356 | B2: Noura Al Kaabi | C2: +971 52 000 0001 | D2: noura.al.kaabi1@example.com | E2: Dubai | F2: oil_change | G2: en | H2: qr | I2: 5 | J2: 5 | K2: yes | L2: 10 | M2: The whole process was easy — booking online, dropping the car, paying by card. | N2: 4 | O2: 4 | P2: 5 | Q2: 5 | R2: 5 | S2: 5 | T2: =ROUND(AVERAGE(I2:J2),2) | U2: =ROUND(AVERAGE(N2:S2),2) | V2: =IF(L2>=9,"promoter",IF(L2>=7,"passive","detractor")) | W2: =IF(OR(V2="detractor",K2<>"yes"),1,0)
A3: 46204.376 | B3: Hind Al Balushi | C3: +971 50 000 0002 | D3: hind.al.balushi2@example.com | E3: Sharjah | F3: brake_repair | G3: en | H3: link | I3: 5 | J3: 4 | K3: yes | L3: 9 | M3: Quoted price was the final price. No surprises on the invoice after the brake job. | N3: 4 | O3: 5 | P3: 5 | Q3: 5 | R3: 5 | S3: 5 | T3: =ROUND(AVERAGE(I3:J3),2) | U3: =ROUND(AVERAGE(N3:S3),2) | V3: =IF(L3>=9,"promoter",IF(L3>=7,"passive","detractor")) | W3: =IF(OR(V3="detractor",K3<>"yes"),1,0)
A4: 46204.392 | B4: Ariel Malik | C4: +971 54 000 0003 | D4: ariel.malik3@example.com | E4: Abu Dhabi | F4: oil_change | G4: en | H4: link | I4: 4 | J4: 4 | K4: partially | L4: 8 | M4: Average experience. Nothing went wrong, nothing stood out either. | N4: 4 | O4: 4 | P4: 4 | Q4: 5 | R4: 5 | S4: 4 | T4: =ROUND(AVERAGE(I4:J4),2) | U4: =ROUND(AVERAGE(N4:S4),2) | V4: =IF(L4>=9,"promoter",IF(L4>=7,"passive","detractor")) | W4: =IF(OR(V4="detractor",K4<>"yes"),1,0) | X4: 46206.351 | Y4: Called and apologised. Technician who handled the job was briefed by the workshop supervisor.
A5: 46204.426 | B5: Faisal Kamau | C5: +971 56 000 0004 | D5: faisal.kamau4@example.com | E5: Al Ain | F5: diagnostic | G5: ar | H5: link | I5: 1 | J5: 1 | K5: yes | L5: 2 | M5: لم يتم حل المشكلة بشكل كامل ولم يتواصل معي أحد. | N5: 1 | O5: 2 | P5: 1 | Q5: 1 | R5: 1 | S5: 1 | T5: =ROUND(AVERAGE(I5:J5),2) | U5: =ROUND(AVERAGE(N5:S5),2) | V5: =IF(L5>=9,"promoter",IF(L5>=7,"passive","detractor")) | W5: =IF(OR(V5="detractor",K5<>"yes"),1,0) | X5: 46205.801 | Y5: Called and apologised. Technician who handled the job was briefed by the workshop supervisor.
A6: 46204.429 | B6: Amal Whitfield | C6: +971 54 000 0005 | D6: amal.whitfield5@example.com | E6: Dubai | F6: general_maintenance | G6: en | H6: staff | I6: 3 | J6: 3 | K6: partially | L6: 8 | M6: Good workmanship. Communication could be better — I had to call twice for an update. | N6: 4 | O6: 5 | P6: 3 | Q6: 4 | R6: 5 | S6: 4 | T6: =ROUND(AVERAGE(I6:J6),2) | U6: =ROUND(AVERAGE(N6:S6),2) | V6: =IF(L6>=9,"promoter",IF(L6>=7,"passive","detractor")) | W6: =IF(OR(V6="detractor",K6<>"yes"),1,0) | X6: 46204.762 | Y6: Discussed the quote variance with the customer; the extra labour line was waived.
A7: 46204.491 | B7: Rashid Aquino | C7: +971 50 000 0006 | D7: rashid.aquino6@example.com | E7: Dubai | F7: oil_change | G7: en | H7: link | I7: 4 | J7: 3 | K7: partially | L7: 8 | M7: Reasonable service. I would like a clearer breakdown of labour versus parts on the invoice. | N7: 5 | O7: 4 | P7: 4 | Q7: 5 | R7: 3 | S7: 4 | T7: =ROUND(AVERAGE(I7:J7),2) | U7: =ROUND(AVERAGE(N7:S7),2) | V7: =IF(L7>=9,"promoter",IF(L7>=7,"passive","detractor")) | W7: =IF(OR(V7="detractor",K7<>"yes"),1,0) | X7: 46206.741 | Y7: Called and apologised. Technician who handled the job was briefed by the workshop supervisor.
A8: 46204.609 | B8: Yousef Mendoza | C8: +971 52 000 0007 | D8: yousef.mendoza7@example.com | E8: Sharjah | F8: general_maintenance | G8: en | H8: link | I8: 4 | J8: 5 | K8: yes | L8: 10 | M8: They followed up a week later to check the car was still running well. | N8: 5 | O8: 4 | P8: 5 | Q8: 5 | R8: 5 | S8: 5 | T8: =ROUND(AVERAGE(I8:J8),2) | U8: =ROUND(AVERAGE(N8:S8),2) | V8: =IF(L8>=9,"promoter",IF(L8>=7,"passive","detractor")) | W8: =IF(OR(V8="detractor",K8<>"yes"),1,0)
A9: 46204.684 | B9: Rajesh Harrison | C9: +971 58 000 0008 | D9: rajesh.harrison8@example.com | E9: Abu Dhabi | F9: general_maintenance | G9: en | H9: link | I9: 2 | J9: 3 | K9: partially | L9: 4 | M9: They could not diagnose the fault and still charged me the full inspection fee. | N9: 3 | O9: 2 | P9: 2 | Q9: 3 | R9: 2 | S9: 1 | T9: =ROUND(AVERAGE(I9:J9),2) | U9: =ROUND(AVERAGE(N9:S9),2) | V9: =IF(L9>=9,"promoter",IF(L9>=7,"passive","detractor")) | W9: =IF(OR(V9="detractor",K9<>"yes"),1,0)
A10: 46204.789 | B10: Manoj Kamau | C10: +971 54 000 0009 | D10: manoj.kamau9@example.com | E10: Dubai | F10: transmission | G10: en | H10: portal | I10: 4 | J10: 5 | K10: yes | L10: 10 | M10: They sent me photos of the old parts before replacing anything. That kind of transparency is rare. | N10: 5 | O10: 5 | P10: 5 | Q10: 5 | R10: 5 | S10: 5 | T10: =ROUND(AVERAGE(I10:J10),2) | U10: =ROUND(AVERAGE(N10:S10),2) | V10: =IF(L10>=9,"promoter",IF(L10>=7,"passive","detractor")) | W10: =IF(OR(V10="detractor",K10<>"yes"),1,0)
A11: 46205.35 | B11: Michael Reddy | C11: +971 50 000 0010 | D11: michael.reddy10@example.com | E11: Dubai | F11: brake_repair | G11: ar | H11: link | I11: 3 | J11: 1 | K11: no | L11: 5 | M11: لم يتم حل المشكلة بشكل كامل ولم يتواصل معي أحد. | N11: 2 | O11: 1 | P11: 1 | Q11: 3 | R11: 3 | S11: 1 | T11: =ROUND(AVERAGE(I11:J11),2) | U11: =ROUND(AVERAGE(N11:S11),2) | V11: =IF(L11>=9,"promoter",IF(L11>=7,"passive","detractor")) | W11: =IF(OR(V11="detractor",K11<>"yes"),1,0) | X11: 46206.641 | Y11: Followed up by phone. Customer declined a return visit but accepted the apology.
A12: 46205.391 | B12: Salma Al Zaabi | C12: +971 55 000 0011 | D12: salma.al.zaabi11@example.com | E12: Sharjah | F12: general_maintenance | G12: en | H12: link | I12: 4 | J12: 4 | K12: yes | L12: 7 | M12: Fine service, though I was not told about an extra charge until I came to pay. | N12: 3 | O12: 3 | P12: 3 | Q12: 2 | R12: 2 | S12: 3 | T12: =ROUND(AVERAGE(I12:J12),2) | U12: =ROUND(AVERAGE(N12:S12),2) | V12: =IF(L12>=9,"promoter",IF(L12>=7,"passive","detractor")) | W12: =IF(OR(V12="detractor",K12<>"yes"),1,0)
A13: 46205.436 | B13: Marife Al Blooshi | C13: +971 50 000 0012 | D13: marife.al.blooshi12@example.com | E13: Abu Dhabi | F13: brake_repair | G13: en | H13: link | I13: 4 | J13: 4 | K13: yes | L13: 9 | M13: Good warranty on the parts and they registered it for me without being asked. | N13: 5 | O13: 5 | P13: 5 | Q13: 5 | R13: 4 | S13: 4 | T13: =ROUND(AVERAGE(I13:J13),2) | U13: =ROUND(AVERAGE(N13:S13),2) | V13: =IF(L13>=9,"promoter",IF(L13>=7,"passive","detractor")) | W13: =IF(OR(V13="detractor",K13<>"yes"),1,0)
A14: 46205.439 | B14: Manoj Mensah | C14: +971 52 000 0013 | D14: manoj.mensah13@example.com | E14: Abu Dhabi | F14: general_maintenance | G14: en | H14: link | I14: 5 | J14: 4 | K14: yes | L14: 9 | M14: Straightforward, no upselling, and the routine service was completed a day early. | N14: 5 | O14: 5 | P14: 5 | Q14: 5 | R14: 5 | S14: 5 | T14: =ROUND(AVERAGE(I14:J14),2) | U14: =ROUND(AVERAGE(N14:S14),2) | V14: =IF(L14>=9,"promoter",IF(L14>=7,"passive","detractor")) | W14: =IF(OR(V14="detractor",K14<>"yes"),1,0)
A15: 46205.462 | B15: Adnan Chandran | C15: +971 55 000 0014 | D15: adnan.chandran14@example.com | E15: Sharjah | F15: engine_repair | G15: en | H15: link | I15: 4 | J15: 4 | K15: yes | L15: 10 | M15: Very satisfied — the invoice was itemised and every line was explained. | N15: 4 | O15: 5 | P15: 5 | Q15: 4 | R15: 5 | S15: 4 | T15: =ROUND(AVERAGE(I15:J15),2) | U15: =ROUND(AVERAGE(N15:S15),2) | V15: =IF(L15>=9,"promoter",IF(L15>=7,"passive","detractor")) | W15: =IF(OR(V15="detractor",K15<>"yes"),1,0)
A16: 46205.479 | B16: Vinu Mathew | C16: +971 50 000 0015 | D16: vinu.mathew15@example.com | E16: Dubai | F16: tire_service | G16: en | H16: link | I16: 4 | J16: 5 | K16: yes | L16: 9 | M16: I have been coming here for three years. the tyre work is always done right the first time. | N16: 3 | O16: 3 | P16: 4 | Q16: 3 | R16: 4 | S16: 4 | T16: =ROUND(AVERAGE(I16:J16),2) | U16: =ROUND(AVERAGE(N16:S16),2) | V16: =IF(L16>=9,"promoter",IF(L16>=7,"passive","detractor")) | W16: =IF(OR(V16="detractor",K16<>"yes"),1,0)
A17: 46205.758 | B17: Shalini Al Mansoori | C17: +971 58 000 0016 | D17: shalini.al.mansoori16@example.com | E17: Sharjah | F17: general_maintenance | G17: en | H17: staff | I17: 4 | J17: 5 | K17: yes | L17: 10 | M17: Best experience I have had with a garage in the UAE. the routine service done properly and on budget. | N17: 5 | O17: 5 | P17: 4 | Q17: 5 | R17: 4 | S17: 4 | T17: =ROUND(AVERAGE(I17:J17),2) | U17: =ROUND(AVERAGE(N17:S17),2) | V17: =IF(L17>=9,"promoter",IF(L17>=7,"passive","detractor")) | W17: =IF(OR(V17="detractor",K17<>"yes"),1,0)
A18: 46205.87 | B18: Fatima Al Yammahi | C18: +971 58 000 0017 | D18: fatima.al.yammahi17@example.com | E18: Al Ain | F18: tire_service | G18: en | H18: link | I18: 5 | J18: 4 | K18: yes | L18: 9 | M18: The service advisor explained exactly what the tyre work needed and what could wait. No pressure to spend more. | N18: 4 | O18: 5 | P18: 4 | Q18: 5 | R18: 5 | S18: 4 | T18: =ROUND(AVERAGE(I18:J18),2) | U18: =ROUND(AVERAGE(N18:S18),2) | V18: =IF(L18>=9,"promoter",IF(L18>=7,"passive","detractor")) | W18: =IF(OR(V18="detractor",K18<>"yes"),1,0)
A19: 46206.485 | B19: Abdulla Mensah | C19: +971 54 000 0018 | D19: abdulla.mensah18@example.com | E19: Sharjah | F19: bodywork | G19: ar | H19: link | I19: 4 | J19: 3 | K19: yes | L19: 7 | M19: العمل جيد لكن الانتظار كان أطول من المتوقع. | N19: 4 | O19: 4 | P19: 4 | Q19: 3 | R19: 5 | S19: 3 | T19: =ROUND(AVERAGE(I19:J19),2) | U19: =ROUND(AVERAGE(N19:S19),2) | V19: =IF(L19>=9,"promoter",IF(L19>=7,"passive","detractor")) | W19: =IF(OR(V19="detractor",K19<>"yes"),1,0)
A20: 46206.706 | B20: Tariq Al Hosani | C20: +971 52 000 0019 | D20: tariq.al.hosani19@example.com | E20: Sharjah | F20: bodywork | G20: ar | H20: qr | I20: 2 | J20: 2 | K20: no | L20: 3 | M20: نفس المشكلة عادت بعد أسبوع واحد واضطررت للرجوع مرة أخرى. | N20: 3 | O20: 2 | P20: 1 | Q20: 2 | R20: 2 | S20: 3 | T20: =ROUND(AVERAGE(I20:J20),2) | U20: =ROUND(AVERAGE(N20:S20),2) | V20: =IF(L20>=9,"promoter",IF(L20>=7,"passive","detractor")) | W20: =IF(OR(V20="detractor",K20<>"yes"),1,0) | X20: 46208.664 | Y20: Arranged collection of the vehicle at our cost to re-inspect the complaint.
A21: 46206.789 | B21: Hamad Rehman | C21: +971 56 000 0020 | D21: hamad.rehman20@example.com | E21: Al Ain | F21: general_maintenance | G21: en | H21: link | I21: 1 | J21: 1 | K21: partially | L21: 5 | M21: the routine service was not completed properly and I had to go elsewhere to have it corrected. | N21: 3 | O21: 3 | P21: 2 | Q21: 3 | R21: 1 | S21: 3 | T21: =ROUND(AVERAGE(I21:J21),2) | U21: =ROUND(AVERAGE(N21:S21),2) | V21: =IF(L21>=9,"promoter",IF(L21>=7,"passive","detractor")) | W21: =IF(OR(V21="detractor",K21<>"yes"),1,0)
A22: 46207.401 | B22: Naveen Sharma | C22: +971 54 000 0021 | D22: naveen.sharma21@example.com | E22: Dubai | F22: general_maintenance | G22: en | H22: qr | I22: 5 | J22: 5 | K22: yes | L22: 9 | M22: They diagnosed in an hour what two other workshops could not find in a week. | N22: 4 | O22: 5 | P22: 5 | Q22: 5 | R22: 5 | S22: 5 | T22: =ROUND(AVERAGE(I22:J22),2) | U22: =ROUND(AVERAGE(N22:S22),2) | V22: =IF(L22>=9,"promoter",IF(L22>=7,"passive","detractor")) | W22: =IF(OR(V22="detractor",K22<>"yes"),1,0)
A23: 46207.401 | B23: Abdulla Al Kaabi | C23: +971 50 000 0022 | D23: abdulla.al.kaabi22@example.com | E23: Abu Dhabi | F23: oil_change | G23: en | H23: portal | I23: 4 | J23: 3 | K23: yes | L23: 8 | M23: Happy with the outcome, less happy with the hour I spent waiting to hand over the keys. | N23: 3 | O23: 3 | P23: 2 | Q23: 2 | R23: 2 | S23: 3 | T23: =ROUND(AVERAGE(I23:J23),2) | U23: =ROUND(AVERAGE(N23:S23),2) | V23: =IF(L23>=9,"promoter",IF(L23>=7,"passive","detractor")) | W23: =IF(OR(V23="detractor",K23<>"yes"),1,0)
A24: 46207.485 | B24: Ariel Al Nuaimi | C24: +971 55 000 0023 | D24: ariel.al.nuaimi23@example.com | E24: Sharjah | F24: oil_change | G24: en | H24: link | I24: 5 | J24: 5 | K24: yes | L24: 10 | M24: Very professional from the first call to handover. Nothing to complain about. | N24: 4 | O24: 4 | P24: 4 | Q24: 4 | R24: 3 | S24: 3 | T24: =ROUND(AVERAGE(I24:J24),2) | U24: =ROUND(AVERAGE(N24:S24),2) | V24: =IF(L24>=9,"promoter",IF(L24>=7,"passive","detractor")) | W24: =IF(OR(V24="detractor",K24<>"yes"),1,0)
A25: 46207.496 | B25: Yousef Aquino | C25: +971 56 000 0024 | D25: yousef.aquino24@example.com | E25: Sharjah | F25: bodywork | G25: en | H25: portal | I25: 4 | J25: 4 | K25: partially | L25: 8 | M25: Work was correct but it took two visits to sort out completely. | N25: 4 | O25: 5 | P25: 3 | Q25: 5 | R25: 4 | S25: 5 | T25: =ROUND(AVERAGE(I25:J25),2) | U25: =ROUND(AVERAGE(N25:S25),2) | V25: =IF(L25>=9,"promoter",IF(L25>=7,"passive","detractor")) | W25: =IF(OR(V25="detractor",K25<>"yes"),1,0)
A26: 46207.567 | B26: Thomas Rehman | C26: +971 56 000 0025 | D26: thomas.rehman25@example.com | E26: Sharjah | F26: tire_service | G26: en | H26: link | I26: 2 | J26: 2 | K26: partially | L26: 6 | M26: Told me the job was done, but the noise I brought it in for is unchanged. | N26: 3 | O26: 3 | P26: 4 | Q26: 2 | R26: 3 | S26: 4 | T26: =ROUND(AVERAGE(I26:J26),2) | U26: =ROUND(AVERAGE(N26:S26),2) | V26: =IF(L26>=9,"promoter",IF(L26>=7,"passive","detractor")) | W26: =IF(OR(V26="detractor",K26<>"yes"),1,0) | X26: 46208.65 | Y26: Customer confirmed the repeat fault was fixed on the return visit and is satisfied now.
A27: 46207.652 | B27: Usman Al Nuaimi | C27: +971 50 000 0026 | D27: usman.al.nuaimi26@example.com | E27: Al Ain | F27: transmission | G27: en | H27: link | I27: 5 | J27: 5 | K27: yes | L27: 10 | M27: Staff are polite and the workmanship on the gearbox work is solid. No issues since. | N27: 5 | O27: 4 | P27: 4 | Q27: 5 | R27: 5 | S27: 5 | T27: =ROUND(AVERAGE(I27:J27),2) | U27: =ROUND(AVERAGE(N27:S27),2) | V27: =IF(L27>=9,"promoter",IF(L27>=7,"passive","detractor")) | W27: =IF(OR(V27="detractor",K27<>"yes"),1,0)
A28: 46207.68 | B28: David Iqbal | C28: +971 50 000 0027 | D28: david.iqbal27@example.com | E28: Abu Dhabi | F28: diagnostic | G28: en | H28: link | I28: 4 | J28: 4 | K28: yes | L28: 8 | M28: Good technical work. The paperwork at collection took much longer than it needed to. | N28: 4 | O28: 3 | P28: 4 | Q28: 4 | R28: 4 | S28: 4 | T28: =ROUND(AVERAGE(I28:J28),2) | U28: =ROUND(AVERAGE(N28:S28),2) | V28: =IF(L28>=9,"promoter",IF(L28>=7,"passive","detractor")) | W28: =IF(OR(V28="detractor",K28<>"yes"),1,0)
A29: 46207.69 | B29: Naeem Malik | C29: +971 58 000 0028 | D29: naeem.malik28@example.com | E29: Abu Dhabi | F29: general_maintenance | G29: en | H29: link | I29: 4 | J29: 3 | K29: partially | L29: 7 | M29: They fixed it, but the first estimate and the second estimate were quite different. | N29: 4 | O29: 4 | P29: 4 | Q29: 4 | R29: 2 | S29: 3 | T29: =ROUND(AVERAGE(I29:J29),2) | U29: =ROUND(AVERAGE(N29:S29),2) | V29: =IF(L29>=9,"promoter",IF(L29>=7,"passive","detractor")) | W29: =IF(OR(V29="detractor",K29<>"yes"),1,0) | X29: 46207.815 | Y29: Reached the customer on the second attempt. Car brought back in and the fault rectified under warranty.
A30: 46207.705 | B30: Mohammed Pillai | C30: +971 58 000 0029 | D30: mohammed.pillai29@example.com | E30: Al Ain | F30: brake_repair | G30: en | H30: link | I30: 4 | J30: 4 | K30: yes | L30: 10 | M30: They fitted me in the same day for an emergency and still finished the brake job on time. | N30: 4 | O30: 4 | P30: 4 | Q30: 4 | R30: 4 | S30: 4 | T30: =ROUND(AVERAGE(I30:J30),2) | U30: =ROUND(AVERAGE(N30:S30),2) | V30: =IF(L30>=9,"promoter",IF(L30>=7,"passive","detractor")) | W30: =IF(OR(V30="detractor",K30<>"yes"),1,0)
A31: 46208.419 | B31: Ibrahim Butt | C31: +971 50 000 0030 | D31: ibrahim.butt30@example.com | E31: Sharjah | F31: oil_change | G31: en | H31: link | I31: 5 | J31: 5 | K31: yes | L31: 10 | M31: WhatsApp updates through the day meant I never had to call and ask. | N31: 5 | O31: 5 | P31: 5 | Q31: 5 | R31: 4 | S31: 5 | T31: =ROUND(AVERAGE(I31:J31),2) | U31: =ROUND(AVERAGE(N31:S31),2) | V31: =IF(L31>=9,"promoter",IF(L31>=7,"passive","detractor")) | W31: =IF(OR(V31="detractor",K31<>"yes"),1,0)
A32: 46208.42 | B32: Deepak Malik | C32: +971 58 000 0031 | D32: deepak.malik31@example.com | E32: Al Ain | F32: oil_change | G32: en | H32: link | I32: 3 | J32: 4 | K32: yes | L32: 7 | M32: The car is running well. The advisor was hard to reach on the phone during the day. | N32: 5 | O32: 4 | P32: 5 | Q32: 4 | R32: 4 | S32: 3 | T32: =ROUND(AVERAGE(I32:J32),2) | U32: =ROUND(AVERAGE(N32:S32),2) | V32: =IF(L32>=9,"promoter",IF(L32>=7,"passive","detractor")) | W32: =IF(OR(V32="detractor",K32<>"yes"),1,0)
A33: 46208.527 | B33: Layla Joseph | C33: +971 54 000 0032 | D33: layla.joseph32@example.com | E33: Abu Dhabi | F33: electrical | G33: en | H33: portal | I33: 4 | J33: 4 | K33: partially | L33: 8 | M33: The repair is good. I only wish they had cleaned the interior after the electrical fault. | N33: 3 | O33: 4 | P33: 5 | Q33: 5 | R33: 3 | S33: 4 | T33: =ROUND(AVERAGE(I33:J33),2) | U33: =ROUND(AVERAGE(N33:S33),2) | V33: =IF(L33>=9,"promoter",IF(L33>=7,"passive","detractor")) | W33: =IF(OR(V33="detractor",K33<>"yes"),1,0) | X33: 46211.361 | Y33: Customer confirmed the repeat fault was fixed on the return visit and is satisfied now.
A34: 46208.601 | B34: Khalid Mendoza | C34: +971 54 000 0033 | D34: khalid.mendoza33@example.com | E34: Sharjah | F34: brake_repair | G34: en | H34: portal | I34: 5 | J34: 5 | K34: yes | L34: 10 | M34: The advisor remembered my car's history and flagged something due next service. Genuinely helpful. | N34: 5 | O34: 5 | P34: 5 | Q34: 5 | R34: 5 | S34: 5 | T34: =ROUND(AVERAGE(I34:J34),2) | U34: =ROUND(AVERAGE(N34:S34),2) | V34: =IF(L34>=9,"promoter",IF(L34>=7,"passive","detractor")) | W34: =IF(OR(V34="detractor",K34<>"yes"),1,0)
A35: 46208.687 | B35: Bilal Malik | C35: +971 56 000 0034 | D35: bilal.malik34@example.com | E35: Abu Dhabi | F35: brake_repair | G35: en | H35: link | I35: 5 | J35: 4 | K35: yes | L35: 9 | M35: Honest team — they told me one part I expected to replace was still fine. | N35: 5 | O35: 4 | P35: 4 | Q35: 5 | R35: 5 | S35: 5 | T35: =ROUND(AVERAGE(I35:J35),2) | U35: =ROUND(AVERAGE(N35:S35),2) | V35: =IF(L35>=9,"promoter",IF(L35>=7,"passive","detractor")) | W35: =IF(OR(V35="detractor",K35<>"yes"),1,0)
A36: 46208.866 | B36: Arun Al Kaabi | C36: +971 50 000 0035 | D36: arun.al.kaabi35@example.com | E36: Dubai | F36: diagnostic | G36: en | H36: link | I36: 5 | J36: 4 | K36: yes | L36: 10 | M36: Booked in the morning and picked the car up the same evening — the diagnostic check was done properly and the price matched the quote. | N36: 5 | O36: 5 | P36: 5 | Q36: 5 | R36: 5 | S36: 5 | T36: =ROUND(AVERAGE(I36:J36),2) | U36: =ROUND(AVERAGE(N36:S36),2) | V36: =IF(L36>=9,"promoter",IF(L36>=7,"passive","detractor")) | W36: =IF(OR(V36="detractor",K36<>"yes"),1,0)
A37: 46209.391 | B37: George Butt | C37: +971 50 000 0036 | D37: george.butt36@example.com | E37: Abu Dhabi | F37: bodywork | G37: en | H37: link | I37: 4 | J37: 4 | K37: yes | L37: 7 | M37: Quality is there. The appointment I booked still meant a 40-minute wait. | N37: 3 | O37: 4 | P37: 3 | Q37: 3 | R37: 2 | S37: 2 | T37: =ROUND(AVERAGE(I37:J37),2) | U37: =ROUND(AVERAGE(N37:S37),2) | V37: =IF(L37>=9,"promoter",IF(L37>=7,"passive","detractor")) | W37: =IF(OR(V37="detractor",K37<>"yes"),1,0)
A38: 46209.491 | B38: Naeem Al Hammadi | C38: +971 56 000 0037 | D38: naeem.al.hammadi37@example.com | E38: Sharjah | F38: bodywork | G38: en | H38: portal | I38: 5 | J38: 4 | K38: yes | L38: 10 | M38: Fair pricing compared to the agency, and the quality of the body repair was just as good. | N38: 4 | O38: 4 | P38: 5 | Q38: 5 | R38: 5 | S38: 5 | T38: =ROUND(AVERAGE(I38:J38),2) | U38: =ROUND(AVERAGE(N38:S38),2) | V38: =IF(L38>=9,"promoter",IF(L38>=7,"passive","detractor")) | W38: =IF(OR(V38="detractor",K38<>"yes"),1,0)
A39: 46209.518 | B39: Manoj Al Yammahi | C39: +971 50 000 0038 | D39: manoj.al.yammahi38@example.com | E39: Abu Dhabi | F39: tire_service | G39: en | H39: link | I39: 4 | J39: 4 | K39: yes | L39: 7 | M39: Overall okay. Slightly expensive for what was done, but the work looks sound. | N39: 4 | O39: 4 | P39: 4 | Q39: 4 | R39: 4 | S39: 3 | T39: =ROUND(AVERAGE(I39:J39),2) | U39: =ROUND(AVERAGE(N39:S39),2) | V39: =IF(L39>=9,"promoter",IF(L39>=7,"passive","detractor")) | W39: =IF(OR(V39="detractor",K39<>"yes"),1,0)
A40: 46209.615 | B40: Paul Al Rashidi | C40: +971 54 000 0039 | D40: paul.al.rashidi39@example.com | E40: Abu Dhabi | F40: tire_service | G40: en | H40: link | I40: 5 | J40: 5 | K40: yes | L40: 10 | M40: Quick, clean and reasonably priced. the tyre work was exactly what I asked for. | N40: 5 | O40: 4 | P40: 5 | Q40: 5 | R40: 5 | S40: 5 | T40: =ROUND(AVERAGE(I40:J40),2) | U40: =ROUND(AVERAGE(N40:S40),2) | V40: =IF(L40>=9,"promoter",IF(L40>=7,"passive","detractor")) | W40: =IF(OR(V40="detractor",K40<>"yes"),1,0)
A41: 46209.636 | B41: Anita Santos | C41: +971 54 000 0040 | D41: anita.santos40@example.com | E41: Sharjah | F41: oil_change | G41: en | H41: link | I41: 4 | J41: 5 | K41: yes | L41: 10 | M41: The technician showed me the problem on the car itself instead of just handing me a bill. | N41: 5 | O41: 5 | P41: 4 | Q41: 5 | R41: 4 | S41: 5 | T41: =ROUND(AVERAGE(I41:J41),2) | U41: =ROUND(AVERAGE(N41:S41),2) | V41: =IF(L41>=9,"promoter",IF(L41>=7,"passive","detractor")) | W41: =IF(OR(V41="detractor",K41<>"yes"),1,0)
A42: 46209.764 | B42: George Al Falasi | C42: +971 56 000 0041 | D42: george.al.falasi41@example.com | E42: Abu Dhabi | F42: brake_repair | G42: en | H42: link | I42: 5 | J42: 4 | K42: yes | L42: 9 | M42: Second opinion after another garage overcharged me. Pioneer did the brake job for half and it has been perfect. | N42: 5 | O42: 5 | P42: 4 | Q42: 5 | R42: 5 | S42: 5 | T42: =ROUND(AVERAGE(I42:J42),2) | U42: =ROUND(AVERAGE(N42:S42),2) | V42: =IF(L42>=9,"promoter",IF(L42>=7,"passive","detractor")) | W42: =IF(OR(V42="detractor",K42<>"yes"),1,0)
A43: 46210.482 | B43: Binu Villanueva | C43: +971 55 000 0042 | D43: binu.villanueva42@example.com | E43: Abu Dhabi | F43: engine_repair | G43: en | H43: link | I43: 4 | J43: 4 | K43: yes | L43: 8 | M43: the engine repair was handled properly. The follow-up on the second issue I raised never came. | N43: 4 | O43: 5 | P43: 4 | Q43: 5 | R43: 5 | S43: 4 | T43: =ROUND(AVERAGE(I43:J43),2) | U43: =ROUND(AVERAGE(N43:S43),2) | V43: =IF(L43>=9,"promoter",IF(L43>=7,"passive","detractor")) | W43: =IF(OR(V43="detractor",K43<>"yes"),1,0)
A44: 46210.511 | B44: Vinod Menon | C44: +971 50 000 0043 | D44: vinod.menon43@example.com | E44: Sharjah | F44: general_maintenance | G44: en | H44: qr | I44: 4 | J44: 4 | K44: yes | L44: 7 | M44: Decent job on the routine service, but nobody called to say the car was ready — I found out when I arrived. | N44: 5 | O44: 4 | P44: 5 | Q44: 4 | R44: 4 | S44: 4 | T44: =ROUND(AVERAGE(I44:J44),2) | U44: =ROUND(AVERAGE(N44:S44),2) | V44: =IF(L44>=9,"promoter",IF(L44>=7,"passive","detractor")) | W44: =IF(OR(V44="detractor",K44<>"yes"),1,0)
A45: 46210.515 | B45: Naveen Al Marzouqi | C45: +971 56 000 0044 | D45: naveen.al.marzouqi44@example.com | E45: Abu Dhabi | F45: diagnostic | G45: en | H45: link | I45: 5 | J45: 5 | K45: yes | L45: 9 | M45: Car came back washed and vacuumed. Small thing, but it shows they care. | N45: 5 | O45: 4 | P45: 5 | Q45: 5 | R45: 5 | S45: 5 | T45: =ROUND(AVERAGE(I45:J45),2) | U45: =ROUND(AVERAGE(N45:S45),2) | V45: =IF(L45>=9,"promoter",IF(L45>=7,"passive","detractor")) | W45: =IF(OR(V45="detractor",K45<>"yes"),1,0)
... A51: 46211.569 | B51: Farhan Ahmed | C51: +971 56 000 0050 | D51: farhan.ahmed50@example.com | E51: Sharjah | F51: tire_service | G51: en | H51: link | I51: 4 | J51: 3 | K51: yes | L51: 7 | M51: Satisfied with the repair itself, though the final bill was a little above the estimate. | N51: 4 | O51: 4 | P51: 4 | Q51: 5 | R51: 4 | S51: 3 | T51: =ROUND(AVERAGE(I51:J51),2) | U51: =ROUND(AVERAGE(N51:S51),2) | V51: =IF(L51>=9,"promoter",IF(L51>=7,"passive","detractor")) | W51: =IF(OR(V51="detractor",K51<>"yes"),1,0)
A52: 46211.704 | B52: Aisha Al Yammahi | C52: +971 50 000 0051 | D52: aisha.al.yammahi51@example.com | E52: Sharjah | F52: brake_repair | G52: en | H52: link | I52: 5 | J52: 4 | K52: partially | L52: 9 | M52: Waiting area is comfortable and the estimate they gave was accurate to the dirham. | N52: 5 | O52: 5 | P52: 5 | Q52: 5 | R52: 4 | S52: 5 | T52: =ROUND(AVERAGE(I52:J52),2) | U52: =ROUND(AVERAGE(N52:S52),2) | V52: =IF(L52>=9,"promoter",IF(L52>=7,"passive","detractor")) | W52: =IF(OR(V52="detractor",K52<>"yes"),1,0) | X52: 46213.495 | Y52: Called the customer, apologised for the delay and booked a free re-check.
A53: 46211.804 | B53: Sajan Al Marzouqi | C53: +971 55 000 0052 | D53: sajan.al.marzouqi52@example.com | E53: Sharjah | F53: brake_repair | G53: en | H53: link | I53: 4 | J53: 4 | K53: yes | L53: 10 | M53: Price, quality and communication were all good. I will not go anywhere else. | N53: 4 | O53: 4 | P53: 3 | Q53: 4 | R53: 4 | S53: 3 | T53: =ROUND(AVERAGE(I53:J53),2) | U53: =ROUND(AVERAGE(N53:S53),2) | V53: =IF(L53>=9,"promoter",IF(L53>=7,"passive","detractor")) | W53: =IF(OR(V53="detractor",K53<>"yes"),1,0)
A54: 46211.872 | B54: Jomar Iyer | C54: +971 54 000 0053 | D54: jomar.iyer53@example.com | E54: Dubai | F54: brake_repair | G54: en | H54: link | I54: 4 | J54: 5 | K54: yes | L54: 10 | M54: Pick-up and drop-off made it easy to get the brake job done without taking leave from work. | N54: 5 | O54: 5 | P54: 5 | Q54: 4 | R54: 4 | S54: 5 | T54: =ROUND(AVERAGE(I54:J54),2) | U54: =ROUND(AVERAGE(N54:S54),2) | V54: =IF(L54>=9,"promoter",IF(L54>=7,"passive","detractor")) | W54: =IF(OR(V54="detractor",K54<>"yes"),1,0)
A55: 46212.472 | B55: Anita Kamau | C55: +971 58 000 0054 | D55: anita.kamau54@example.com | E55: Sharjah | F55: electrical | G55: en | H55: qr | I55: 5 | J55: 5 | K55: yes | L55: 9 | M55: Excellent work on the electrical fault. Already recommended them to two colleagues at work. | N55: 5 | O55: 5 | P55: 4 | Q55: 5 | R55: 5 | S55: 5 | T55: =ROUND(AVERAGE(I55:J55),2) | U55: =ROUND(AVERAGE(N55:S55),2) | V55: =IF(L55>=9,"promoter",IF(L55>=7,"passive","detractor")) | W55: =IF(OR(V55="detractor",K55<>"yes"),1,0)
A56: 46212.589 | B56: Marife Aquino | C56: +971 56 000 0055 | D56: marife.aquino55@example.com | E56: Sharjah | F56: transmission | G56: en | H56: link | I56: 1 | J56: 2 | K56: no | L56: 4 | M56: Poor communication throughout. I had to keep coming to the branch in person to get answers. | N56: 1 | O56: 2 | P56: 2 | Q56: 1 | R56: 1 | S56: 2 | T56: =ROUND(AVERAGE(I56:J56),2) | U56: =ROUND(AVERAGE(N56:S56),2) | V56: =IF(L56>=9,"promoter",IF(L56>=7,"passive","detractor")) | W56: =IF(OR(V56="detractor",K56<>"yes"),1,0)
A57: 46213.497 | B57: Michael Nair | C57: +971 50 000 0056 | D57: michael.nair56@example.com | E57: Abu Dhabi | F57: oil_change | G57: en | H57: link | I57: 5 | J57: 4 | K57: yes | L57: 10 | M57: The technician showed me the problem on the car itself instead of just handing me a bill. | N57: 5 | O57: 4 | P57: 5 | Q57: 5 | R57: 4 | S57: 4 | T57: =ROUND(AVERAGE(I57:J57),2) | U57: =ROUND(AVERAGE(N57:S57),2) | V57: =IF(L57>=9,"promoter",IF(L57>=7,"passive","detractor")) | W57: =IF(OR(V57="detractor",K57<>"yes"),1,0)
A58: 46213.721 | B58: Stephen Mendoza | C58: +971 58 000 0057 | D58: stephen.mendoza57@example.com | E58: Sharjah | F58: brake_repair | G58: en | H58: link | I58: 5 | J58: 4 | K58: yes | L58: 10 | M58: Honest team — they told me one part I expected to replace was still fine. | N58: 5 | O58: 5 | P58: 5 | Q58: 4 | R58: 5 | S58: 5 | T58: =ROUND(AVERAGE(I58:J58),2) | U58: =ROUND(AVERAGE(N58:S58),2) | V58: =IF(L58>=9,"promoter",IF(L58>=7,"passive","detractor")) | W58: =IF(OR(V58="detractor",K58<>"yes"),1,0)
A59: 46213.78 | B59: Meera Butt | C59: +971 52 000 0058 | D59: meera.butt58@example.com | E59: Al Ain | F59: oil_change | G59: en | H59: link | I59: 5 | J59: 5 | K59: yes | L59: 9 | M59: Quoted price was the final price. No surprises on the invoice after the oil and filter change. | N59: 5 | O59: 5 | P59: 5 | Q59: 5 | R59: 4 | S59: 5 | T59: =ROUND(AVERAGE(I59:J59),2) | U59: =ROUND(AVERAGE(N59:S59),2) | V59: =IF(L59>=9,"promoter",IF(L59>=7,"passive","detractor")) | W59: =IF(OR(V59="detractor",K59<>"yes"),1,0)
A60: 46214.355 | B60: Waleed Reddy | C60: +971 55 000 0059 | D60: waleed.reddy59@example.com | E60: Abu Dhabi | F60: diagnostic | G60: en | H60: link | I60: 5 | J60: 5 | K60: yes | L60: 9 | M60: They followed up a week later to check the car was still running well. | N60: 5 | O60: 5 | P60: 5 | Q60: 4 | R60: 5 | S60: 5 | T60: =ROUND(AVERAGE(I60:J60),2) | U60: =ROUND(AVERAGE(N60:S60),2) | V60: =IF(L60>=9,"promoter",IF(L60>=7,"passive","detractor")) | W60: =IF(OR(V60="detractor",K60<>"yes"),1,0)
A61: 46214.513 | B61: Yousef Al Hammadi | C61: +971 56 000 0060 | D61: yousef.al.hammadi60@example.com | E61: Sharjah | F61: general_maintenance | G61: en | H61: portal | I61: 4 | J61: 4 | K61: yes | L61: 9 | M61: The whole process was easy — booking online, dropping the car, paying by card. | N61: 4 | O61: 5 | P61: 5 | Q61: 4 | R61: 5 | S61: 5 | T61: =ROUND(AVERAGE(I61:J61),2) | U61: =ROUND(AVERAGE(N61:S61),2) | V61: =IF(L61>=9,"promoter",IF(L61>=7,"passive","detractor")) | W61: =IF(OR(V61="detractor",K61<>"yes"),1,0)
A62: 46214.861 | B62: Omar Al Ali | C62: +971 52 000 0061 | D62: omar.al.ali61@example.com | E62: Dubai | F62: general_maintenance | G62: en | H62: link | I62: 5 | J62: 4 | K62: yes | L62: 9 | M62: They fitted me in the same day for an emergency and still finished the routine service on time. | N62: 5 | O62: 5 | P62: 4 | Q62: 5 | R62: 5 | S62: 5 | T62: =ROUND(AVERAGE(I62:J62),2) | U62: =ROUND(AVERAGE(N62:S62),2) | V62: =IF(L62>=9,"promoter",IF(L62>=7,"passive","detractor")) | W62: =IF(OR(V62="detractor",K62<>"yes"),1,0)
A63: 46215.395 | B63: Emma Al Rashidi | C63: +971 55 000 0062 | D63: emma.al.rashidi62@example.com | E63: Abu Dhabi | F63: oil_change | G63: en | H63: qr | I63: 2 | J63: 2 | K63: no | L63: 5 | M63: Overcharged compared to the quote and the attitude at the desk was dismissive. | N63: 3 | O63: 4 | P63: 3 | Q63: 2 | R63: 3 | S63: 2 | T63: =ROUND(AVERAGE(I63:J63),2) | U63: =ROUND(AVERAGE(N63:S63),2) | V63: =IF(L63>=9,"promoter",IF(L63>=7,"passive","detractor")) | W63: =IF(OR(V63="detractor",K63<>"yes"),1,0) | X63: 46216.395 | Y63: Customer contacted; branch manager reviewed the invoice and issued a partial credit.
A64: 46215.404 | B64: Emma Villanueva | C64: +971 54 000 0063 | D64: emma.villanueva63@example.com | E64: Dubai | F64: brake_repair | G64: en | H64: qr | I64: 4 | J64: 4 | K64: yes | L64: 7 | M64: the brake job is fine. Parking at the branch is difficult when you arrive after nine. | N64: 4 | O64: 4 | P64: 5 | Q64: 4 | R64: 4 | S64: 3 | T64: =ROUND(AVERAGE(I64:J64),2) | U64: =ROUND(AVERAGE(N64:S64),2) | V64: =IF(L64>=9,"promoter",IF(L64>=7,"passive","detractor")) | W64: =IF(OR(V64="detractor",K64<>"yes"),1,0)
A65: 46215.443 | B65: Shibu Menon | C65: +971 58 000 0064 | D65: shibu.menon64@example.com | E65: Abu Dhabi | F65: tire_service | G65: en | H65: link | I65: 5 | J65: 4 | K65: yes | L65: 10 | M65: I have been coming here for three years. the tyre work is always done right the first time. | N65: 4 | O65: 4 | P65: 5 | Q65: 5 | R65: 5 | S65: 5 | T65: =ROUND(AVERAGE(I65:J65),2) | U65: =ROUND(AVERAGE(N65:S65),2) | V65: =IF(L65>=9,"promoter",IF(L65>=7,"passive","detractor")) | W65: =IF(OR(V65="detractor",K65<>"yes"),1,0)
A66: 46215.447 | B66: Prakash Kamau | C66: +971 52 000 0065 | D66: prakash.kamau65@example.com | E66: Al Ain | F66: oil_change | G66: en | H66: qr | I66: 4 | J66: 3 | K66: yes | L66: 8 | M66: No complaints about the quality, but the reception area gets very crowded in the morning. | N66: 5 | O66: 4 | P66: 5 | Q66: 4 | R66: 4 | S66: 3 | T66: =ROUND(AVERAGE(I66:J66),2) | U66: =ROUND(AVERAGE(N66:S66),2) | V66: =IF(L66>=9,"promoter",IF(L66>=7,"passive","detractor")) | W66: =IF(OR(V66="detractor",K66<>"yes"),1,0)
A67: 46215.464 | B67: Marife Sullivan | C67: +971 50 000 0066 | D67: marife.sullivan66@example.com | E67: Abu Dhabi | F67: bodywork | G67: en | H67: link | I67: 5 | J67: 5 | K67: yes | L67: 9 | M67: Very clean workshop and the staff actually listen. the body repair was finished ahead of the time they promised. | N67: 5 | O67: 4 | P67: 4 | Q67: 5 | R67: 5 | S67: 5 | T67: =ROUND(AVERAGE(I67:J67),2) | U67: =ROUND(AVERAGE(N67:S67),2) | V67: =IF(L67>=9,"promoter",IF(L67>=7,"passive","detractor")) | W67: =IF(OR(V67="detractor",K67<>"yes"),1,0)
A68: 46215.597 | B68: Shibu Joseph | C68: +971 50 000 0067 | D68: shibu.joseph67@example.com | E68: Sharjah | F68: brake_repair | G68: en | H68: link | I68: 4 | J68: 4 | K68: yes | L68: 8 | M68: Solid work. The branch could use more staff at the service desk in the mornings. | N68: 4 | O68: 5 | P68: 4 | Q68: 5 | R68: 4 | S68: 4 | T68: =ROUND(AVERAGE(I68:J68),2) | U68: =ROUND(AVERAGE(N68:S68),2) | V68: =IF(L68>=9,"promoter",IF(L68>=7,"passive","detractor")) | W68: =IF(OR(V68="detractor",K68<>"yes"),1,0)
A69: 46215.612 | B69: Hassan Al Falasi | C69: +971 58 000 0068 | D69: hassan.al.falasi68@example.com | E69: Al Ain | F69: tire_service | G69: en | H69: link | I69: 4 | J69: 4 | K69: yes | L69: 7 | M69: Reasonable. I would use them again for the tyre work but would confirm the price in writing first. | N69: 5 | O69: 4 | P69: 4 | Q69: 4 | R69: 4 | S69: 4 | T69: =ROUND(AVERAGE(I69:J69),2) | U69: =ROUND(AVERAGE(N69:S69),2) | V69: =IF(L69>=9,"promoter",IF(L69>=7,"passive","detractor")) | W69: =IF(OR(V69="detractor",K69<>"yes"),1,0)
A70: 46215.75 | B70: Ibrahim Malik | C70: +971 50 000 0069 | D70: ibrahim.malik69@example.com | E70: Abu Dhabi | F70: diagnostic | G70: en | H70: link | I70: 4 | J70: 4 | K70: yes | L70: 8 | M70: the diagnostic check is fine. Parking at the branch is difficult when you arrive after nine. | N70: 4 | O70: 5 | P70: 4 | Q70: 4 | R70: 4 | S70: 5 | T70: =ROUND(AVERAGE(I70:J70),2) | U70: =ROUND(AVERAGE(N70:S70),2) | V70: =IF(L70>=9,"promoter",IF(L70>=7,"passive","detractor")) | W70: =IF(OR(V70="detractor",K70<>"yes"),1,0)
A71: 46215.781 | B71: Peter Reyes | C71: +971 50 000 0070 | D71: peter.reyes70@example.com | E71: Abu Dhabi | F71: general_maintenance | G71: en | H71: portal | I71: 5 | J71: 5 | K71: yes | L71: 10 | M71: Car came back washed and vacuumed. Small thing, but it shows they care. | N71: 5 | O71: 5 | P71: 5 | Q71: 4 | R71: 5 | S71: 4 | T71: =ROUND(AVERAGE(I71:J71),2) | U71: =ROUND(AVERAGE(N71:S71),2) | V71: =IF(L71>=9,"promoter",IF(L71>=7,"passive","detractor")) | W71: =IF(OR(V71="detractor",K71<>"yes"),1,0)
A72: 46215.79 | B72: Divya Nair | C72: +971 56 000 0071 | D72: divya.nair71@example.com | E72: Sharjah | F72: tire_service | G72: en | H72: link | I72: 4 | J72: 4 | K72: partially | L72: 7 | M72: Work was correct but it took two visits to sort out completely. | N72: 3 | O72: 3 | P72: 3 | Q72: 3 | R72: 3 | S72: 4 | T72: =ROUND(AVERAGE(I72:J72),2) | U72: =ROUND(AVERAGE(N72:S72),2) | V72: =IF(L72>=9,"promoter",IF(L72>=7,"passive","detractor")) | W72: =IF(OR(V72="detractor",K72<>"yes"),1,0) | X72: 46218.581 | Y72: Customer confirmed the repeat fault was fixed on the return visit and is satisfied now.
A73: 46215.802 | B73: Bilal Al Falasi | C73: +971 55 000 0072 | D73: bilal.al.falasi72@example.com | E73: Dubai | F73: oil_change | G73: en | H73: link | I73: 3 | J73: 3 | K73: partially | L73: 5 | M73: Same warning light came on two days after the oil and filter change. Had to bring it back twice. | N73: 1 | O73: 2 | P73: 3 | Q73: 2 | R73: 2 | S73: 1 | T73: =ROUND(AVERAGE(I73:J73),2) | U73: =ROUND(AVERAGE(N73:S73),2) | V73: =IF(L73>=9,"promoter",IF(L73>=7,"passive","detractor")) | W73: =IF(OR(V73="detractor",K73<>"yes"),1,0) | X73: 46218.427 | Y73: Discussed the quote variance with the customer; the extra labour line was waived.
A74: 46215.847 | B74: David Villanueva | C74: +971 56 000 0073 | D74: david.villanueva73@example.com | E74: Abu Dhabi | F74: other | G74: en | H74: link | I74: 5 | J74: 5 | K74: partially | L74: 10 | M74: Waiting area is comfortable and the estimate they gave was accurate to the dirham. | N74: 5 | O74: 5 | P74: 5 | Q74: 5 | R74: 4 | S74: 5 | T74: =ROUND(AVERAGE(I74:J74),2) | U74: =ROUND(AVERAGE(N74:S74),2) | V74: =IF(L74>=9,"promoter",IF(L74>=7,"passive","detractor")) | W74: =IF(OR(V74="detractor",K74<>"yes"),1,0)
A75: 46216.37 | B75: Manoj Krishnan | C75: +971 54 000 0074 | D75: manoj.krishnan74@example.com | E75: Dubai | F75: engine_repair | G75: en | H75: link | I75: 4 | J75: 5 | K75: yes | L75: 9 | M75: Staff are polite and the workmanship on the engine repair is solid. No issues since. | N75: 5 | O75: 5 | P75: 4 | Q75: 5 | R75: 5 | S75: 5 | T75: =ROUND(AVERAGE(I75:J75),2) | U75: =ROUND(AVERAGE(N75:S75),2) | V75: =IF(L75>=9,"promoter",IF(L75>=7,"passive","detractor")) | W75: =IF(OR(V75="detractor",K75<>"yes"),1,0)
A76: 46216.388 | B76: Tariq Kumar | C76: +971 58 000 0075 | D76: tariq.kumar75@example.com | E76: Al Ain | F76: electrical | G76: en | H76: link | I76: 4 | J76: 3 | K76: yes | L76: 8 | M76: Quality is there. The appointment I booked still meant a 40-minute wait. | N76: 4 | O76: 3 | P76: 4 | Q76: 4 | R76: 4 | S76: 4 | T76: =ROUND(AVERAGE(I76:J76),2) | U76: =ROUND(AVERAGE(N76:S76),2) | V76: =IF(L76>=9,"promoter",IF(L76>=7,"passive","detractor")) | W76: =IF(OR(V76="detractor",K76<>"yes"),1,0)
A77: 46216.394 | B77: Ariel Al Suwaidi | C77: +971 54 000 0076 | D77: ariel.al.suwaidi76@example.com | E77: Dubai | F77: bodywork | G77: en | H77: portal | I77: 5 | J77: 5 | K77: yes | L77: 10 | M77: Good warranty on the parts and they registered it for me without being asked. | N77: 5 | O77: 5 | P77: 4 | Q77: 5 | R77: 5 | S77: 5 | T77: =ROUND(AVERAGE(I77:J77),2) | U77: =ROUND(AVERAGE(N77:S77),2) | V77: =IF(L77>=9,"promoter",IF(L77>=7,"passive","detractor")) | W77: =IF(OR(V77="detractor",K77<>"yes"),1,0)
A78: 46216.415 | B78: Joselito Okonkwo | C78: +971 58 000 0077 | D78: joselito.okonkwo77@example.com | E78: Abu Dhabi | F78: electrical | G78: en | H78: link | I78: 4 | J78: 3 | K78: yes | L78: 7 | M78: Good workmanship. Communication could be better — I had to call twice for an update. | N78: 3 | O78: 4 | P78: 5 | Q78: 5 | R78: 3 | S78: 4 | T78: =ROUND(AVERAGE(I78:J78),2) | U78: =ROUND(AVERAGE(N78:S78),2) | V78: =IF(L78>=9,"promoter",IF(L78>=7,"passive","detractor")) | W78: =IF(OR(V78="detractor",K78<>"yes"),1,0)
A79: 46216.456 | B79: Sarah Harrison | C79: +971 56 000 0078 | D79: sarah.harrison78@example.com | E79: Sharjah | F79: engine_repair | G79: en | H79: link | I79: 5 | J79: 5 | K79: yes | L79: 10 | M79: Best experience I have had with a garage in the UAE. the engine repair done properly and on budget. | N79: 4 | O79: 4 | P79: 4 | Q79: 4 | R79: 3 | S79: 4 | T79: =ROUND(AVERAGE(I79:J79),2) | U79: =ROUND(AVERAGE(N79:S79),2) | V79: =IF(L79>=9,"promoter",IF(L79>=7,"passive","detractor")) | W79: =IF(OR(V79="detractor",K79<>"yes"),1,0)
A80: 46216.49 | B80: Arun Abebe | C80: +971 54 000 0079 | D80: arun.abebe79@example.com | E80: Abu Dhabi | F80: bodywork | G80: en | H80: link | I80: 5 | J80: 4 | K80: yes | L80: 10 | M80: Very satisfied — the invoice was itemised and every line was explained. | N80: 4 | O80: 5 | P80: 5 | Q80: 5 | R80: 5 | S80: 4 | T80: =ROUND(AVERAGE(I80:J80),2) | U80: =ROUND(AVERAGE(N80:S80),2) | V80: =IF(L80>=9,"promoter",IF(L80>=7,"passive","detractor")) | W80: =IF(OR(V80="detractor",K80<>"yes"),1,0)
A81: 46216.686 | B81: Sunil Villanueva | C81: +971 50 000 0080 | D81: sunil.villanueva80@example.com | E81: Abu Dhabi | F81: brake_repair | G81: en | H81: portal | I81: 5 | J81: 5 | K81: partially | L81: 10 | M81: The advisor remembered my car's history and flagged something due next service. Genuinely helpful. | N81: 5 | O81: 5 | P81: 5 | Q81: 5 | R81: 5 | S81: 5 | T81: =ROUND(AVERAGE(I81:J81),2) | U81: =ROUND(AVERAGE(N81:S81),2) | V81: =IF(L81>=9,"promoter",IF(L81>=7,"passive","detractor")) | W81: =IF(OR(V81="detractor",K81<>"yes"),1,0) | X81: 46218.77 | Y81: Discussed the quote variance with the customer; the extra labour line was waived.
A82: 46216.713 | B82: Shibu Kamau | C82: +971 55 000 0081 | D82: shibu.kamau81@example.com | E82: Abu Dhabi | F82: tire_service | G82: en | H82: link | I82: 4 | J82: 4 | K82: yes | L82: 10 | M82: They sent me photos of the old parts before replacing anything. That kind of transparency is rare. | N82: 5 | O82: 5 | P82: 5 | Q82: 5 | R82: 5 | S82: 4 | T82: =ROUND(AVERAGE(I82:J82),2) | U82: =ROUND(AVERAGE(N82:S82),2) | V82: =IF(L82>=9,"promoter",IF(L82>=7,"passive","detractor")) | W82: =IF(OR(V82="detractor",K82<>"yes"),1,0)
A83: 46217.368 | B83: Naeem Abebe | C83: +971 58 000 0082 | D83: naeem.abebe82@example.com | E83: Dubai | F83: tire_service | G83: en | H83: link | I83: 5 | J83: 5 | K83: yes | L83: 10 | M83: Reception called me twice with updates without me having to chase them. | N83: 5 | O83: 5 | P83: 5 | Q83: 5 | R83: 4 | S83: 5 | T83: =ROUND(AVERAGE(I83:J83),2) | U83: =ROUND(AVERAGE(N83:S83),2) | V83: =IF(L83>=9,"promoter",IF(L83>=7,"passive","detractor")) | W83: =IF(OR(V83="detractor",K83<>"yes"),1,0)
A84: 46217.454 | B84: Ahmed Al Zaabi | C84: +971 50 000 0083 | D84: ahmed.al.zaabi83@example.com | E84: Dubai | F84: general_maintenance | G84: en | H84: portal | I84: 1 | J84: 2 | K84: partially | L84: 2 | M84: Paid for the routine service and the fault returned immediately. Still waiting for a resolution. | N84: 3 | O84: 3 | P84: 3 | Q84: 4 | R84: 3 | S84: 3 | T84: =ROUND(AVERAGE(I84:J84),2) | U84: =ROUND(AVERAGE(N84:S84),2) | V84: =IF(L84>=9,"promoter",IF(L84>=7,"passive","detractor")) | W84: =IF(OR(V84="detractor",K84<>"yes"),1,0)
A85: 46217.632 | B85: Naveen Al Mansoori | C85: +971 55 000 0084 | D85: naveen.al.mansoori84@example.com | E85: Dubai | F85: brake_repair | G85: en | H85: qr | I85: 4 | J85: 4 | K85: yes | L85: 8 | M85: The car is running well. The advisor was hard to reach on the phone during the day. | N85: 5 | O85: 4 | P85: 4 | Q85: 4 | R85: 4 | S85: 3 | T85: =ROUND(AVERAGE(I85:J85),2) | U85: =ROUND(AVERAGE(N85:S85),2) | V85: =IF(L85>=9,"promoter",IF(L85>=7,"passive","detractor")) | W85: =IF(OR(V85="detractor",K85<>"yes"),1,0)
A86: 46218.469 | B86: Naeem Malik | C86: +971 52 000 0085 | D86: naeem.malik85@example.com | E86: Abu Dhabi | F86: bodywork | G86: en | H86: link | I86: 4 | J86: 4 | K86: yes | L86: 7 | M86: They fixed it, but the first estimate and the second estimate were quite different. | N86: 3 | O86: 4 | P86: 4 | Q86: 5 | R86: 3 | S86: 3 | T86: =ROUND(AVERAGE(I86:J86),2) | U86: =ROUND(AVERAGE(N86:S86),2) | V86: =IF(L86>=9,"promoter",IF(L86>=7,"passive","detractor")) | W86: =IF(OR(V86="detractor",K86<>"yes"),1,0)
A87: 46218.508 | B87: Aisha Malik | C87: +971 54 000 0086 | D87: aisha.malik86@example.com | E87: Abu Dhabi | F87: tire_service | G87: en | H87: link | I87: 3 | J87: 2 | K87: partially | L87: 6 | M87: Car was returned with a warning light that was not there when I dropped it off. | N87: 1 | O87: 2 | P87: 1 | Q87: 1 | R87: 2 | S87: 1 | T87: =ROUND(AVERAGE(I87:J87),2) | U87: =ROUND(AVERAGE(N87:S87),2) | V87: =IF(L87>=9,"promoter",IF(L87>=7,"passive","detractor")) | W87: =IF(OR(V87="detractor",K87<>"yes"),1,0)
A88: 46218.72 | B88: Faisal Cruz | C88: +971 58 000 0087 | D88: faisal.cruz87@example.com | E88: Sharjah | F88: general_maintenance | G88: en | H88: staff | I88: 4 | J88: 4 | K88: yes | L88: 7 | M88: Average experience. Nothing went wrong, nothing stood out either. | N88: 2 | O88: 2 | P88: 3 | Q88: 3 | R88: 3 | S88: 3 | T88: =ROUND(AVERAGE(I88:J88),2) | U88: =ROUND(AVERAGE(N88:S88),2) | V88: =IF(L88>=9,"promoter",IF(L88>=7,"passive","detractor")) | W88: =IF(OR(V88="detractor",K88<>"yes"),1,0)
A89: 46218.753 | B89: Vijay Varghese | C89: +971 54 000 0088 | D89: vijay.varghese88@example.com | E89: Abu Dhabi | F89: brake_repair | G89: en | H89: link | I89: 4 | J89: 5 | K89: yes | L89: 9 | M89: Fair pricing compared to the agency, and the quality of the brake job was just as good. | N89: 5 | O89: 4 | P89: 5 | Q89: 5 | R89: 5 | S89: 5 | T89: =ROUND(AVERAGE(I89:J89),2) | U89: =ROUND(AVERAGE(N89:S89),2) | V89: =IF(L89>=9,"promoter",IF(L89>=7,"passive","detractor")) | W89: =IF(OR(V89="detractor",K89<>"yes"),1,0)
A90: 46219.382 | B90: Emma Harrison | C90: +971 52 000 0089 | D90: emma.harrison89@example.com | E90: Dubai | F90: transmission | G90: en | H90: link | I90: 5 | J90: 4 | K90: yes | L90: 10 | M90: Price, quality and communication were all good. I will not go anywhere else. | N90: 5 | O90: 5 | P90: 5 | Q90: 4 | R90: 5 | S90: 5 | T90: =ROUND(AVERAGE(I90:J90),2) | U90: =ROUND(AVERAGE(N90:S90),2) | V90: =IF(L90>=9,"promoter",IF(L90>=7,"passive","detractor")) | W90: =IF(OR(V90="detractor",K90<>"yes"),1,0)
A91: 46219.419 | B91: Sajan Qureshi | C91: +971 58 000 0090 | D91: sajan.qureshi90@example.com | E91: Al Ain | F91: general_maintenance | G91: en | H91: link | I91: 5 | J91: 5 | K91: yes | L91: 10 | M91: Very professional from the first call to handover. Nothing to complain about. | N91: 5 | O91: 5 | P91: 5 | Q91: 4 | R91: 5 | S91: 5 | T91: =ROUND(AVERAGE(I91:J91),2) | U91: =ROUND(AVERAGE(N91:S91),2) | V91: =IF(L91>=9,"promoter",IF(L91>=7,"passive","detractor")) | W91: =IF(OR(V91="detractor",K91<>"yes"),1,0)
A92: 46219.438 | B92: Priya Al Mansoori | C92: +971 50 000 0091 | D92: priya.al.mansoori91@example.com | E92: Al Ain | F92: engine_repair | G92: en | H92: link | I92: 5 | J92: 5 | K92: yes | L92: 10 | M92: Booked in the morning and picked the car up the same evening — the engine repair was done properly and the price matched the quote. | N92: 5 | O92: 5 | P92: 5 | Q92: 5 | R92: 4 | S92: 4 | T92: =ROUND(AVERAGE(I92:J92),2) | U92: =ROUND(AVERAGE(N92:S92),2) | V92: =IF(L92>=9,"promoter",IF(L92>=7,"passive","detractor")) | W92: =IF(OR(V92="detractor",K92<>"yes"),1,0)
A93: 46219.561 | B93: Yousef Al Falasi | C93: +971 56 000 0092 | D93: yousef.al.falasi92@example.com | E93: Sharjah | F93: general_maintenance | G93: en | H93: link | I93: 3 | J93: 3 | K93: no | L93: 5 | M93: Charged for a part that I later found had not been replaced. Very disappointing. | N93: 2 | O93: 1 | P93: 2 | Q93: 1 | R93: 1 | S93: 2 | T93: =ROUND(AVERAGE(I93:J93),2) | U93: =ROUND(AVERAGE(N93:S93),2) | V93: =IF(L93>=9,"promoter",IF(L93>=7,"passive","detractor")) | W93: =IF(OR(V93="detractor",K93<>"yes"),1,0) | X93: 46222.352 | Y93: Called the customer, apologised for the delay and booked a free re-check.
A94: 46219.627 | B94: Naveen Al Zaabi | C94: +971 50 000 0093 | D94: naveen.al.zaabi93@example.com | E94: Al Ain | F94: electrical | G94: ar | H94: link | I94: 5 | J94: 4 | K94: yes | L94: 9 | M94: أفضل ورشة تعاملت معها. العمل متقن والأسعار معقولة. | N94: 4 | O94: 4 | P94: 3 | Q94: 4 | R94: 4 | S94: 3 | T94: =ROUND(AVERAGE(I94:J94),2) | U94: =ROUND(AVERAGE(N94:S94),2) | V94: =IF(L94>=9,"promoter",IF(L94>=7,"passive","detractor")) | W94: =IF(OR(V94="detractor",K94<>"yes"),1,0)
A95: 46219.749 | B95: Deepak Al Hosani | C95: +971 58 000 0094 | D95: deepak.al.hosani94@example.com | E95: Sharjah | F95: tire_service | G95: ar | H95: link | I95: 4 | J95: 4 | K95: yes | L95: 7 | M95: راضٍ عن الإصلاح، لكن التواصل يحتاج إلى تحسين. | N95: 4 | O95: 4 | P95: 5 | Q95: 4 | R95: 3 | S95: 3 | T95: =ROUND(AVERAGE(I95:J95),2) | U95: =ROUND(AVERAGE(N95:S95),2) | V95: =IF(L95>=9,"promoter",IF(L95>=7,"passive","detractor")) | W95: =IF(OR(V95="detractor",K95<>"yes"),1,0)
A96: 46219.837 | B96: Mohammed Abebe | C96: +971 50 000 0095 | D96: mohammed.abebe95@example.com | E96: Abu Dhabi | F96: electrical | G96: en | H96: link | I96: 4 | J96: 3 | K96: yes | L96: 7 | M96: Good technical work. The paperwork at collection took much longer than it needed to. | N96: 5 | O96: 5 | P96: 5 | Q96: 4 | R96: 4 | S96: 4 | T96: =ROUND(AVERAGE(I96:J96),2) | U96: =ROUND(AVERAGE(N96:S96),2) | V96: =IF(L96>=9,"promoter",IF(L96>=7,"passive","detractor")) | W96: =IF(OR(V96="detractor",K96<>"yes"),1,0)
A97: 46219.854 | B97: Paul Al Zaabi | C97: +971 50 000 0096 | D97: paul.al.zaabi96@example.com | E97: Abu Dhabi | F97: diagnostic | G97: en | H97: link | I97: 5 | J97: 4 | K97: yes | L97: 9 | M97: Second opinion after another garage overcharged me. Pioneer did the diagnostic check for half and it has been perfect. | N97: 5 | O97: 4 | P97: 5 | Q97: 5 | R97: 5 | S97: 5 | T97: =ROUND(AVERAGE(I97:J97),2) | U97: =ROUND(AVERAGE(N97:S97),2) | V97: =IF(L97>=9,"promoter",IF(L97>=7,"passive","detractor")) | W97: =IF(OR(V97="detractor",K97<>"yes"),1,0)
A98: 46220.407 | B98: Reynaldo Al Zaabi | C98: +971 54 000 0097 | D98: reynaldo.al.zaabi97@example.com | E98: Dubai | F98: oil_change | G98: en | H98: link | I98: 4 | J98: 5 | K98: partially | L98: 10 | M98: They kept the old parts to show me, explained the warranty, and answered every question. | N98: 4 | O98: 4 | P98: 3 | Q98: 4 | R98: 4 | S98: 3 | T98: =ROUND(AVERAGE(I98:J98),2) | U98: =ROUND(AVERAGE(N98:S98),2) | V98: =IF(L98>=9,"promoter",IF(L98>=7,"passive","detractor")) | W98: =IF(OR(V98="detractor",K98<>"yes"),1,0) | X98: 46222.699 | Y98: Spoke to the customer, valeted the interior free of charge and apologised for the condition at handover.
A99: 46220.497 | B99: Paul Khan | C99: +971 50 000 0098 | D99: paul.khan98@example.com | E99: Dubai | F99: oil_change | G99: en | H99: portal | I99: 4 | J99: 4 | K99: yes | L99: 10 | M99: WhatsApp updates through the day meant I never had to call and ask. | N99: 5 | O99: 5 | P99: 5 | Q99: 4 | R99: 5 | S99: 5 | T99: =ROUND(AVERAGE(I99:J99),2) | U99: =ROUND(AVERAGE(N99:S99),2) | V99: =IF(L99>=9,"promoter",IF(L99>=7,"passive","detractor")) | W99: =IF(OR(V99="detractor",K99<>"yes"),1,0)
A100: 46220.747 | B100: Faisal Al Suwaidi | C100: +971 55 000 0099 | D100: faisal.al.suwaidi99@example.com | E100: Abu Dhabi | F100: general_maintenance | G100: en | H100: qr | I100: 5 | J100: 4 | K100: yes | L100: 9 | M100: Straightforward, no upselling, and the routine service was completed a day early. | N100: 5 | O100: 5 | P100: 5 | Q100: 4 | R100: 5 | S100: 4 | T100: =ROUND(AVERAGE(I100:J100),2) | U100: =ROUND(AVERAGE(N100:S100),2) | V100: =IF(L100>=9,"promoter",IF(L100>=7,"passive","detractor")) | W100: =IF(OR(V100="detractor",K100<>"yes"),1,0)
A101: 46221.503 | B101: Meera Bautista | C101: +971 58 000 0100 | D101: meera.bautista100@example.com | E101: Abu Dhabi | F101: electrical | G101: en | H101: link | I101: 4 | J101: 5 | K101: yes | L101: 10 | M101: The service advisor explained exactly what the electrical fault needed and what could wait. No pressure to spend more. | N101: 4 | O101: 4 | P101: 4 | Q101: 4 | R101: 4 | S101: 4 | T101: =ROUND(AVERAGE(I101:J101),2) | U101: =ROUND(AVERAGE(N101:S101),2) | V101: =IF(L101>=9,"promoter",IF(L101>=7,"passive","detractor")) | W101: =IF(OR(V101="detractor",K101<>"yes"),1,0)
A102: 46221.529 | B102: Hind Thomas | C102: +971 55 000 0101 | D102: hind.thomas101@example.com | E102: Abu Dhabi | F102: oil_change | G102: en | H102: link | I102: 5 | J102: 5 | K102: yes | L102: 10 | M102: Pick-up and drop-off made it easy to get the oil and filter change done without taking leave from work. | N102: 4 | O102: 4 | P102: 5 | Q102: 5 | R102: 5 | S102: 5 | T102: =ROUND(AVERAGE(I102:J102),2) | U102: =ROUND(AVERAGE(N102:S102),2) | V102: =IF(L102>=9,"promoter",IF(L102>=7,"passive","detractor")) | W102: =IF(OR(V102="detractor",K102<>"yes"),1,0)
A103: 46221.543 | B103: George Qureshi | C103: +971 52 000 0102 | D103: george.qureshi102@example.com | E103: Al Ain | F103: diagnostic | G103: en | H103: link | I103: 3 | J103: 2 | K103: partially | L103: 6 | M103: Interior was left dirty with grease on the steering wheel and seat. | N103: 1 | O103: 2 | P103: 2 | Q103: 1 | R103: 1 | S103: 1 | T103: =ROUND(AVERAGE(I103:J103),2) | U103: =ROUND(AVERAGE(N103:S103),2) | V103: =IF(L103>=9,"promoter",IF(L103>=7,"passive","detractor")) | W103: =IF(OR(V103="detractor",K103<>"yes"),1,0) | X103: 46223.418 | Y103: Customer confirmed the repeat fault was fixed on the return visit and is satisfied now.
A104: 46221.76 | B104: Binu Al Hosani | C104: +971 58 000 0103 | D104: binu.al.hosani103@example.com | E104: Dubai | F104: electrical | G104: en | H104: link | I104: 3 | J104: 2 | K104: partially | L104: 3 | M104: The final invoice was well above the quote and no one could tell me why. | N104: 4 | O104: 2 | P104: 3 | Q104: 3 | R104: 2 | S104: 3 | T104: =ROUND(AVERAGE(I104:J104),2) | U104: =ROUND(AVERAGE(N104:S104),2) | V104: =IF(L104>=9,"promoter",IF(L104>=7,"passive","detractor")) | W104: =IF(OR(V104="detractor",K104<>"yes"),1,0) | X104: 46222.468 | Y104: Discussed the quote variance with the customer; the extra labour line was waived.
A105: 46221.843 | B105: Kavita Al Marzouqi | C105: +971 56 000 0104 | D105: kavita.al.marzouqi104@example.com | E105: Dubai | F105: general_maintenance | G105: en | H105: qr | I105: 4 | J105: 5 | K105: yes | L105: 10 | M105: Excellent work on the routine service. Already recommended them to two colleagues at work. | N105: 5 | O105: 5 | P105: 5 | Q105: 5 | R105: 4 | S105: 5 | T105: =ROUND(AVERAGE(I105:J105),2) | U105: =ROUND(AVERAGE(N105:S105),2) | V105: =IF(L105>=9,"promoter",IF(L105>=7,"passive","detractor")) | W105: =IF(OR(V105="detractor",K105<>"yes"),1,0)
...

Sheet Monthly Summary
A1: Pioneer Car Service Center — Customer Experience, July 2026
A2: Synthetic dataset. See the Notes sheet before using these figures anywhere.
A4: Headline measures
A5: Responses received | B5: =COUNTA(Responses!$B$2:$B$165)
A6: Net Promoter Score | B6: =ROUND((COUNTIF(Responses!$V$2:$V$165,"promoter")-COUNTIF(Responses!$V$2:$V$165,"detractor"))/COUNTA(Responses!$V$2:$V$165)*100,0)
A7: Customer satisfaction (mean of 5) | B7: =ROUND(AVERAGE(Responses!$U$2:$U$165),2)
A8: Customer Effort Score (mean of 5) | B8: =ROUND(AVERAGE(Responses!$T$2:$T$165),2)
A9: Mean recommendation score (of 10) | B9: =ROUND(AVERAGE(Responses!$L$2:$L$165),2)
A10: Fully resolved | B10: =ROUND(COUNTIF(Responses!$K$2:$K$165,"yes")/COUNTA(Responses!$K$2:$K$165)*100,1)
A11: Flagged for follow-up | B11: =SUM(Responses!$W$2:$W$165)
A12: Follow-up completed | B12: =COUNT(Responses!$X$2:$X$165)
A13: Follow-up still outstanding | B13: =B11-B12
A15: NPS breakdown | C15: Share
A16: Promoters | B16: =COUNTIF(Responses!$V$2:$V$165,"promoter") | C16: =ROUND(B16/$B$5*100,1)
A17: Passives | B17: =COUNTIF(Responses!$V$2:$V$165,"passive") | C17: =ROUND(B17/$B$5*100,1)
A18: Detractors | B18: =COUNTIF(Responses!$V$2:$V$165,"detractor") | C18: =ROUND(B18/$B$5*100,1)
A20: By branch
A21: Branch | B21: Responses | C21: NPS | D21: CSAT | E21: CES
A22: Abu Dhabi | B22: =COUNTIF(Responses!$E$2:$E$165,$A22) | C22: =IF(B22=0,"",ROUND((COUNTIFS(Responses!$E$2:$E$165,$A22,Responses!$V$2:$V$165,"promoter")-COUNTIFS(Responses!$E$2:$E$165,$A22,Responses!$V$2:$V$165,"detractor"))/B22*100,0)) | D22: =IF(B22=0,"",ROUND(AVERAGEIF(Responses!$E$2:$E$165,$A22,Responses!$U$2:$U$165),2)) | E22: =IF(B22=0,"",ROUND(AVERAGEIF(Responses!$E$2:$E$165,$A22,Responses!$T$2:$T$165),2))
A23: Sharjah | B23: =COUNTIF(Responses!$E$2:$E$165,$A23) | C23: =IF(B23=0,"",ROUND((COUNTIFS(Responses!$E$2:$E$165,$A23,Responses!$V$2:$V$165,"promoter")-COUNTIFS(Responses!$E$2:$E$165,$A23,Responses!$V$2:$V$165,"detractor"))/B23*100,0)) | D23: =IF(B23=0,"",ROUND(AVERAGEIF(Responses!$E$2:$E$165,$A23,Responses!$U$2:$U$165),2)) | E23: =IF(B23=0,"",ROUND(AVERAGEIF(Responses!$E$2:$E$165,$A23,Responses!$T$2:$T$165),2))
A24: Dubai | B24: =COUNTIF(Responses!$E$2:$E$165,$A24) | C24: =IF(B24=0,"",ROUND((COUNTIFS(Responses!$E$2:$E$165,$A24,Responses!$V$2:$V$165,"promoter")-COUNTIFS(Responses!$E$2:$E$165,$A24,Responses!$V$2:$V$165,"detractor"))/B24*100,0)) | D24: =IF(B24=0,"",ROUND(AVERAGEIF(Responses!$E$2:$E$165,$A24,Responses!$U$2:$U$165),2)) | E24: =IF(B24=0,"",ROUND(AVERAGEIF(Responses!$E$2:$E$165,$A24,Responses!$T$2:$T$165),2))
A25: Al Ain | B25: =COUNTIF(Responses!$E$2:$E$165,$A25) | C25: =IF(B25=0,"",ROUND((COUNTIFS(Responses!$E$2:$E$165,$A25,Responses!$V$2:$V$165,"promoter")-COUNTIFS(Responses!$E$2:$E$165,$A25,Responses!$V$2:$V$165,"detractor"))/B25*100,0)) | D25: =IF(B25=0,"",ROUND(AVERAGEIF(Responses!$E$2:$E$165,$A25,Responses!$U$2:$U$165),2)) | E25: =IF(B25=0,"",ROUND(AVERAGEIF(Responses!$E$2:$E$165,$A25,Responses!$T$2:$T$165),2))
A27: By service
A28: Service | B28: Responses | C28: NPS | D28: CSAT
A29: oil_change | B29: =COUNTIF(Responses!$F$2:$F$165,$A29) | C29: =IF(B29=0,"",ROUND((COUNTIFS(Responses!$F$2:$F$165,$A29,Responses!$V$2:$V$165,"promoter")-COUNTIFS(Responses!$F$2:$F$165,$A29,Responses!$V$2:$V$165,"detractor"))/B29*100,0)) | D29: =IF(B29=0,"",ROUND(AVERAGEIF(Responses!$F$2:$F$165,$A29,Responses!$U$2:$U$165),2))
A30: general_maintenance | B30: =COUNTIF(Responses!$F$2:$F$165,$A30) | C30: =IF(B30=0,"",ROUND((COUNTIFS(Responses!$F$2:$F$165,$A30,Responses!$V$2:$V$165,"promoter")-COUNTIFS(Responses!$F$2:$F$165,$A30,Responses!$V$2:$V$165,"detractor"))/B30*100,0)) | D30: =IF(B30=0,"",ROUND(AVERAGEIF(Responses!$F$2:$F$165,$A30,Responses!$U$2:$U$165),2))
A31: tire_service | B31: =COUNTIF(Responses!$F$2:$F$165,$A31) | C31: =IF(B31=0,"",ROUND((COUNTIFS(Responses!$F$2:$F$165,$A31,Responses!$V$2:$V$165,"promoter")-COUNTIFS(Responses!$F$2:$F$165,$A31,Responses!$V$2:$V$165,"detractor"))/B31*100,0)) | D31: =IF(B31=0,"",ROUND(AVERAGEIF(Responses!$F$2:$F$165,$A31,Responses!$U$2:$U$165),2))
A32: brake_repair | B32: =COUNTIF(Responses!$F$2:$F$165,$A32) | C32: =IF(B32=0,"",ROUND((COUNTIFS(Responses!$F$2:$F$165,$A32,Responses!$V$2:$V$165,"promoter")-COUNTIFS(Responses!$F$2:$F$165,$A32,Responses!$V$2:$V$165,"detractor"))/B32*100,0)) | D32: =IF(B32=0,"",ROUND(AVERAGEIF(Responses!$F$2:$F$165,$A32,Responses!$U$2:$U$165),2))
A33: engine_repair | B33: =COUNTIF(Responses!$F$2:$F$165,$A33) | C33: =IF(B33=0,"",ROUND((COUNTIFS(Responses!$F$2:$F$165,$A33,Responses!$V$2:$V$165,"promoter")-COUNTIFS(Responses!$F$2:$F$165,$A33,Responses!$V$2:$V$165,"detractor"))/B33*100,0)) | D33: =IF(B33=0,"",ROUND(AVERAGEIF(Responses!$F$2:$F$165,$A33,Responses!$U$2:$U$165),2))
A34: electrical | B34: =COUNTIF(Responses!$F$2:$F$165,$A34) | C34: =IF(B34=0,"",ROUND((COUNTIFS(Responses!$F$2:$F$165,$A34,Responses!$V$2:$V$165,"promoter")-COUNTIFS(Responses!$F$2:$F$165,$A34,Responses!$V$2:$V$165,"detractor"))/B34*100,0)) | D34: =IF(B34=0,"",ROUND(AVERAGEIF(Responses!$F$2:$F$165,$A34,Responses!$U$2:$U$165),2))
A35: bodywork | B35: =COUNTIF(Responses!$F$2:$F$165,$A35) | C35: =IF(B35=0,"",ROUND((COUNTIFS(Responses!$F$2:$F$165,$A35,Responses!$V$2:$V$165,"promoter")-COUNTIFS(Responses!$F$2:$F$165,$A35,Responses!$V$2:$V$165,"detractor"))/B35*100,0)) | D35: =IF(B35=0,"",ROUND(AVERAGEIF(Responses!$F$2:$F$165,$A35,Responses!$U$2:$U$165),2))
A36: diagnostic | B36: =COUNTIF(Responses!$F$2:$F$165,$A36) | C36: =IF(B36=0,"",ROUND((COUNTIFS(Responses!$F$2:$F$165,$A36,Responses!$V$2:$V$165,"promoter")-COUNTIFS(Responses!$F$2:$F$165,$A36,Responses!$V$2:$V$165,"detractor"))/B36*100,0)) | D36: =IF(B36=0,"",ROUND(AVERAGEIF(Responses!$F$2:$F$165,$A36,Responses!$U$2:$U$165),2))
A37: transmission | B37: =COUNTIF(Responses!$F$2:$F$165,$A37) | C37: =IF(B37=0,"",ROUND((COUNTIFS(Responses!$F$2:$F$165,$A37,Responses!$V$2:$V$165,"promoter")-COUNTIFS(Responses!$F$2:$F$165,$A37,Responses!$V$2:$V$165,"detractor"))/B37*100,0)) | D37: =IF(B37=0,"",ROUND(AVERAGEIF(Responses!$F$2:$F$165,$A37,Responses!$U$2:$U$165),2))
A38: other | B38: =COUNTIF(Responses!$F$2:$F$165,$A38) | C38: =IF(B38=0,"",ROUND((COUNTIFS(Responses!$F$2:$F$165,$A38,Responses!$V$2:$V$165,"promoter")-COUNTIFS(Responses!$F$2:$F$165,$A38,Responses!$V$2:$V$165,"detractor"))/B38*100,0)) | D38: =IF(B38=0,"",ROUND(AVERAGEIF(Responses!$F$2:$F$165,$A38,Responses!$U$2:$U$165),2))
A40: Formulas read the Responses sheet directly — change a row there and every figure above updates when the workbook recalculates.

Sheet Notes
A1: Pioneer Car Service Center — CX survey dataset, July 2026
A3: What this is
A4: 164 customer survey responses covering 1–31 July 2026, in the exact column shape of the survey_responses table. Every row has a respondent name, a branch and a service, which is what the Customer Experience dashboard needs in order to show per-branch and per-service breakdowns.
A6: These respondents are not real customers
A7: The names, scores and comments were generated for demonstration and testing. They are not the words of any Pioneer customer and must not be reported as voice-of-customer evidence, quoted in a management pack, or mixed into a real CX report without saying where they came from.
A9: Contact details cannot reach anyone, by design
A10: Phone numbers use the +971 5x 000 0xxx block, which is not an assigned UAE subscriber range, so no number here can connect to a real person. Emails use example.com, reserved by RFC 2606 and permanently undeliverable. This matters because the CX workflow asks staff to call flagged detractors back — with real-looking numbers, a demo would eventually dial a stranger.
A12: How the numbers were shaped
A13: Roughly 57% promoters, 27% passives and 16% detractors, giving an NPS near +41. CSAT and CES answers are drawn to agree with each row's NPS band, so a promoter does not score 2s. Dates are weekday-weighted for the UAE working week (Friday lightest) and fall in workshop hours. Detractors and any response that was not fully resolved are flagged, and about 78% of those carry a completed follow-up with a recorded outcome.
A15: Loading it
A16: node scripts/import-survey-responses.js --file=<this file> --dry-run
A17: Drop --dry-run to write. The importer recomputes ces_avg, csat_avg, nps_category and is_flagged from the answer columns rather than trusting the sheet, and stamps user_agent with a seed marker.
... A24: Generated with a fixed random seed (20260701), so regenerating produces this same sheet rather than a different one.
